{
    "authors": [
        {
            "name": "J.K. Rowling",
            "author_id": 1,
            "date_of_birth": "1965-07-31",
            "nationality": "British"
        },
        {
            "name": "Haruki Murakami",
            "author_id": 2,
            "date_of_birth": "1949-01-12",
            "nationality": "Japanese"
        },
        {
            "name": "Stephen King",
            "author_id": 3,
            "date_of_birth": "1947-09-21",
            "nationality": "American"
        }
    ],
    "books": [
        {
            "book_id": 1,
            "title": "Harry Potter and the Philosopher's Stone",
            "isbn": "9780747532743",
            "publication_date": "1997-06-26",
            "genre": "Fantasy",
            "pages": 223,
            "author_id": 1
        },
        {
            "book_id": 2,
            "title": "Harry Potter and the Chamber of Secrets",
            "isbn": "9780747538486",
            "publication_date": "1998-07-02",
            "genre": "Fantasy",
            "pages": 251,
            "author_id": 1
        },
        {
            "book_id": 3,
            "title": "Kafka on the Shore",
            "isbn": "9781400079278",
            "publication_date": "2002-09-12",
            "genre": "Magical Realism",
            "pages": 480,
            "author_id": 2
        },
        {
            "book_id": 4,
            "title": "The Shining",
            "isbn": "9780385121675",
            "publication_date": "1977-01-28",
            "genre": "Horror",
            "pages": 447,
            "author_id": 3
        },
        {
            "book_id": 5,
            "title": "It",
            "isbn": "9780450411434",
            "publication_date": "1986-09-15",
            "genre": "Horror",
            "pages": 1138,
            "author_id": 3
        }
    ]
}